{
    "bomFormat": "CycloneDX",
    "specVersion": "1.6",
    "serialNumber": "urn:uuid:35511e4b-3973-45a1-bd09-5434b562f5e4",
    "version": 1,
    "metadata": {
        "timestamp": "2025-02-28T12:08:37.510919+00:00",
        "component": {
            "type": "machine-learning-model",
            "bom-ref": "shenzhi-wang/Llama3.1-8B-Chinese-Chat-a666da60-fc0f-52bf-8301-13a09be9fb7d",
            "name": "shenzhi-wang/Llama3.1-8B-Chinese-Chat",
            "licenses": [
                {
                    "license": {
                        "name": "llama3.1"
                    }
                }
            ],
            "externalReferences": [
                {
                    "url": "https://huggingface.co/shenzhi-wang/Llama3.1-8B-Chinese-Chat",
                    "type": "documentation"
                }
            ],
            "modelCard": {
                "modelParameters": {
                    "task": "text-generation",
                    "architectureFamily": "llama",
                    "modelArchitecture": "LlamaForCausalLM",
                    "datasets": []
                },
                "properties": [
                    {
                        "name": "library_name",
                        "value": "transformers"
                    },
                    {
                        "name": "base_model",
                        "value": "meta-llama/Meta-Llama-3.1-8B-Instruct"
                    }
                ]
            },
            "authors": [
                {
                    "name": "shenzhi-wang"
                }
            ],
            "description": "# Model Summary\n\nllama3.1-8B-Chinese-Chat is an instruction-tuned language model for Chinese & English users with various abilities such as roleplaying & tool-using built upon the Meta-Llama-3.1-8B-Instruct model.\n\nDevelopers: [Shenzhi Wang](https://shenzhi-wang.netlify.app)\\*, [Yaowei Zheng](https://github.com/hiyouga)\\*, Guoyin Wang (in.ai), Shiji Song, Gao Huang. (\\*: Equal Contribution)\n\n- License: [Llama-3.1 License](https://huggingface.co/meta-llama/Meta-Llama-3.1-8B/blob/main/LICENSE)\n- Base Model: Meta-Llama-3.1-8B-Instruct\n- Model Size: 8.03B\n- Context length: 128K (reported by [Meta-Llama-3.1-8B-Instruct model](https://huggingface.co/meta-llama/Meta-Llama-3.1-8B-Instruct), untested for our Chinese model)\n",
            "tags": [
                "transformers",
                "safetensors",
                "gguf",
                "llama",
                "text-generation",
                "llama-factory",
                "orpo",
                "conversational",
                "en",
                "zh",
                "arxiv:2403.07691",
                "base_model:meta-llama/Llama-3.1-8B-Instruct",
                "base_model:quantized:meta-llama/Llama-3.1-8B-Instruct",
                "doi:10.57967/hf/2779",
                "license:llama3.1",
                "autotrain_compatible",
                "text-generation-inference",
                "endpoints_compatible",
                "region:us"
            ]
        }
    },
    "components": []
}